{
    "AX": {
        "error": 0.003930179253808056,
        "error_type": "SEM",
        "filter_outliers_dict": {
            "filter_outliers": true,
            "iterations": 1,
            "std_devs": 2
        },
        "fit": "Average",
        "fn": 111,
        "include_baseline_error": false,
        "n": 120,
        "reviewed": true,
        "value": -0.17894202551326235
    },
    "CDD": {
        "error": 3.691316739300783e-06,
        "error_type": "SEM",
        "filter_outliers_dict": {
            "filter_outliers": true,
            "iterations": 1,
            "std_devs": 10
        },
        "fit": "Average",
        "fn": 120,
        "include_baseline_error": false,
        "n": 120,
        "reviewed": true,
        "value": 1.1466069190646522e-05
    },
    "H1": {
        "error": 0.003422514243031894,
        "error_type": "SEM",
        "filter_outliers_dict": {
            "filter_outliers": true,
            "iterations": 1,
            "std_devs": 2
        },
        "fit": "Average",
        "fn": 114,
        "include_baseline_error": false,
        "n": 120,
        "reviewed": true,
        "value": -0.003473072890764135
    },
    "H2": {
        "error": 0.0033005038610871944,
        "error_type": "SEM",
        "filter_outliers_dict": {
            "filter_outliers": true,
            "iterations": 1,
            "std_devs": 2
        },
        "fit": "average",
        "value": -0.028787482684565137
    },
    "L1": {
        "error": 0.0035724323750453003,
        "error_type": "SEM",
        "filter_outliers_dict": {
            "filter_outliers": true,
            "iterations": 1,
            "std_devs": 2
        },
        "fit": "Average",
        "fn": 111,
        "include_baseline_error": false,
        "n": 120,
        "reviewed": true,
        "value": 0.004030890752678593
    },
    "L2": {
        "error": 0.004202504256689391,
        "error_type": "SEM",
        "filter_outliers_dict": {
            "filter_outliers": true,
            "iterations": 1,
            "std_devs": 2
        },
        "fit": "Average",
        "fn": 114,
        "include_baseline_error": false,
        "n": 120,
        "reviewed": true,
        "value": 0.033797286832786835
    }
}