{
    "Ar36": {
        "error": 0.00017032745692150656,
        "error_type": "SEM",
        "filter_outliers_dict": {
            "filter_outliers": true,
            "iterations": 1,
            "std_devs": 2
        },
        "fit": "Parabolic",
        "value": 0.004425665984444476
    },
    "Ar37": {
        "error": 0.004894649711436445,
        "error_type": "SEM",
        "filter_outliers_dict": {
            "filter_outliers": true,
            "iterations": 1,
            "std_devs": 2
        },
        "fit": "linear",
        "value": 0.06154331624558783
    },
    "Ar38": {
        "error": 0.003972124745863459,
        "error_type": "SEM",
        "filter_outliers_dict": {
            "filter_outliers": true,
            "iterations": 1,
            "std_devs": 2
        },
        "fit": "linear",
        "value": 0.04758063873303359
    },
    "Ar39": {
        "error": 0.009292125487153333,
        "error_type": "SEM",
        "filter_outliers_dict": {
            "filter_outliers": true,
            "iterations": 1,
            "std_devs": 2
        },
        "fit": "Parabolic",
        "value": 2.8556618326314465
    },
    "Ar40": {
        "error": 0.008444195172162508,
        "error_type": "SEM",
        "filter_outliers_dict": {
            "filter_outliers": true,
            "iterations": 1,
            "std_devs": 2
        },
        "fit": "Parabolic",
        "value": 10.81666339342161
    },
    "Ar41": {
        "error": 0.00445625296693703,
        "error_type": "SEM",
        "filter_outliers_dict": {
            "filter_outliers": true,
            "iterations": 1,
            "std_devs": 2
        },
        "fit": "linear",
        "value": -0.018610870860167043
    }
}