{
    "Ar36": {
        "error": 0.00021751193045762727,
        "error_type": "SEM",
        "filter_outliers_dict": {
            "filter_outliers": true,
            "iterations": 1,
            "std_devs": 2
        },
        "fit": "Parabolic",
        "fn": 380,
        "include_baseline_error": false,
        "n": 400,
        "reviewed": true,
        "value": 0.012133618805641873
    },
    "Ar37": {
        "error": 0.004794995072056132,
        "error_type": "SEM",
        "filter_outliers_dict": {
            "filter_outliers": true,
            "iterations": 1,
            "std_devs": 2
        },
        "fit": "Linear",
        "fn": 384,
        "include_baseline_error": false,
        "n": 400,
        "reviewed": true,
        "value": 0.08452648733626886
    },
    "Ar38": {
        "error": 0.004483433523724134,
        "error_type": "SEM",
        "filter_outliers_dict": {
            "filter_outliers": true,
            "iterations": 1,
            "std_devs": 2
        },
        "fit": "Linear",
        "fn": 387,
        "include_baseline_error": false,
        "n": 400,
        "reviewed": true,
        "value": 0.5913766063981868
    },
    "Ar39": {
        "error": 0.012330185849403267,
        "error_type": "SEM",
        "filter_outliers_dict": {
            "filter_outliers": true,
            "iterations": 1,
            "std_devs": 2
        },
        "fit": "Parabolic",
        "fn": 385,
        "include_baseline_error": false,
        "n": 400,
        "reviewed": true,
        "value": 47.15743887216426
    },
    "Ar40": {
        "error": 0.015378702078273842,
        "error_type": "SEM",
        "filter_outliers_dict": {
            "filter_outliers": true,
            "iterations": 1,
            "std_devs": 2
        },
        "fit": "Parabolic",
        "fn": 383,
        "include_baseline_error": false,
        "n": 400,
        "reviewed": true,
        "value": 150.3290854839849
    },
    "Ar41": {
        "error": 0.004857506834567623,
        "error_type": "SEM",
        "filter_outliers_dict": {
            "filter_outliers": true,
            "iterations": 1,
            "std_devs": 2
        },
        "fit": "linear",
        "value": -0.008370639423266523
    }
}