{
    "Ar36": {
        "error": 0.0007932607420021097,
        "error_type": "SEM",
        "filter_outliers_dict": {
            "filter_outliers": true,
            "iterations": 1,
            "std_devs": 2
        },
        "fit": "Parabolic",
        "fn": 326,
        "include_baseline_error": false,
        "n": 340,
        "reviewed": true,
        "value": 0.07154526868795157
    },
    "Ar37": {
        "error": 0.014002283576633372,
        "error_type": "SEM",
        "filter_outliers_dict": {
            "filter_outliers": true,
            "iterations": 1,
            "std_devs": 2
        },
        "fit": "Linear",
        "fn": 325,
        "include_baseline_error": false,
        "n": 340,
        "reviewed": true,
        "value": 1.5448813504292684
    },
    "Ar38": {
        "error": 0.005497266775783374,
        "error_type": "SEM",
        "filter_outliers_dict": {
            "filter_outliers": true,
            "iterations": 1,
            "std_devs": 2
        },
        "fit": "Linear",
        "fn": 326,
        "include_baseline_error": false,
        "n": 340,
        "reviewed": true,
        "value": 0.06276312494662667
    },
    "Ar39": {
        "error": 0.013304431736709288,
        "error_type": "SEM",
        "filter_outliers_dict": {
            "filter_outliers": true,
            "iterations": 1,
            "std_devs": 2
        },
        "fit": "Parabolic",
        "fn": 324,
        "include_baseline_error": false,
        "n": 340,
        "reviewed": true,
        "value": 1.1168336460030277
    },
    "Ar40": {
        "error": 0.03162187521343117,
        "error_type": "SEM",
        "filter_outliers_dict": {
            "filter_outliers": true,
            "iterations": 1,
            "std_devs": 2
        },
        "fit": "Parabolic",
        "fn": 330,
        "include_baseline_error": false,
        "n": 340,
        "reviewed": true,
        "value": 52.90863415115948
    }
}