{
    "Ar36":{
        "error":0.0001744133,
        "error_type":"SEM",
        "filter_outliers_dict":{
            "filter_outliers":true,
            "iterations":1,
            "std_devs":2
        },
        "fit":"Parabolic",
        "value":0.0037906063
    },
    "Ar37":{
        "error":0.0046552432,
        "error_type":"SEM",
        "filter_outliers_dict":{
            "filter_outliers":true,
            "iterations":1,
            "std_devs":2
        },
        "fit":"linear",
        "value":0.0779275357
    },
    "Ar38":{
        "error":0.0022632834,
        "error_type":"SEM",
        "filter_outliers_dict":{
            "filter_outliers":true,
            "iterations":1,
            "std_devs":2
        },
        "fit":"linear",
        "value":0.1460138063
    },
    "Ar39":{
        "error":0.010664639,
        "error_type":"SEM",
        "filter_outliers_dict":{
            "filter_outliers":true,
            "iterations":1,
            "std_devs":2
        },
        "fit":"Parabolic",
        "value":14.1928905428
    },
    "Ar40":{
        "error":0.0089215853,
        "error_type":"SEM",
        "filter_outliers_dict":{
            "filter_outliers":true,
            "iterations":1,
            "std_devs":2
        },
        "fit":"Parabolic",
        "value":16.9438689308
    },
    "Ar41":{
        "error":0.0113947804,
        "error_type":"SEM",
        "filter_outliers_dict":{
            "filter_outliers":true,
            "iterations":1,
            "std_devs":2
        },
        "fit":"linear",
        "value":0.0469940369
    }
}